openrgb/Network.py
openrgb/ORGBDevice.py
openrgb/OpenRGB.py
openrgb/__init__.py
openrgb/binreader.py
openrgb/consts.py
openrgb/utils.py
OpenRGB_PyClient-0.1.1.dist-info/LICENSE
OpenRGB_PyClient-0.1.1.dist-info/METADATA
OpenRGB_PyClient-0.1.1.dist-info/WHEEL
OpenRGB_PyClient-0.1.1.dist-info/top_level.txt
OpenRGB_PyClient-0.1.1.dist-info/RECORD
