Metadata-Version: 2.1
Name: OpenRGB-PyClient
Version: 0.1.1
Summary: Python Client for the OpenRGB SDK Server
Home-page: https://github.com/bahorn/OpenRGB-PyClient
Author: B Horn
Author-email: b@horn.uk
License: UNKNOWN
Platform: UNKNOWN
Classifier: Programming Language :: Python :: 3
Classifier: License :: OSI Approved :: MIT License
Classifier: Operating System :: OS Independent
Requires-Python: >=3.6
